clyde/__init__.py
clyde/applications.py
clyde/client.py
clyde/datastructures.py
clyde/endpoints.py
clyde/enums.py
clyde/middleware.py
clyde/models.py
clyde/responses.py
clyde/routing.py
clyde/sessions.py
clyde/utils.py
clyde-0.1.0.dist-info/LICENSE
clyde-0.1.0.dist-info/WHEEL
clyde-0.1.0.dist-info/METADATA
clyde-0.1.0.dist-info/RECORD
