Metadata-Version: 2.1
Name: clyde
Version: 0.1.0
Summary: 
License: MIT
Author: Tom Bulled
Author-email: 26026015+tombulled@users.noreply.github.com
Requires-Python: >=3.8,<4.0
Classifier: License :: OSI Approved :: MIT License
Classifier: Programming Language :: Python :: 3
Classifier: Programming Language :: Python :: 3.8
Classifier: Programming Language :: Python :: 3.9
Requires-Dist: attrs (>=21.1.0,<22.0.0)
Requires-Dist: httpx (>=0.18.1,<0.19.0)
Requires-Dist: pydantic (>=1.8.1,<2.0.0)
